{
  "baseComponentFileName": "codesp",
  "baseComponentName": "vscs-codesp",
  "baseEnvironmentFileName": "codesp.prod",
  "baseEnvironmentName": "vscs-codesp-prod",
  "baseFileName": "codesp.prod-ops-rel",
  "baseInstanceFileName": "codesp.prod-ops-rel",
  "baseInstanceName": "vscs-codesp-prod-ops-rel",
  "baseName": "vscs-codesp-prod-ops-rel",
  "basePlaneFileName": "codesp.prod-ops",
  "basePlaneName": "vscs-codesp-prod-ops",
  "component": "codesp",
  "env": "prod",
  "instance": "rel",
  "instanceLocation": "WestUs2",
  "instanceRegions": [
    "ap-se",
    "eu-w",
    "us-e",
    "us-w2"
  ],
  "plane": "ops",
  "prefix": "vscs",
  "subscriptionId": "5f625617-0786-46cc-815e-c969b3f01e12",
  "subscriptionName": "vscs-codesp-prod-ops"
}